fachiipdf/__init__.py
fachiipdf/pdf2image.py
fachiipdf/pdf2text.py
fachiipdf-1.0.dist-info/LICENSE
fachiipdf-1.0.dist-info/METADATA
fachiipdf-1.0.dist-info/WHEEL
fachiipdf-1.0.dist-info/top_level.txt
fachiipdf-1.0.dist-info/RECORD
